pyCoalesce/__init__.py
pyCoalesce/coalesce_request.py
pyCoalesce/classes/__init__.py
pyCoalesce/classes/coalesce_entity.py
pyCoalesce/classes/coalesce_entity_template.py
pyCoalesce/classes/coalesce_json.py
pyCoalesce/classes/entity.py
pyCoalesce/classes/entity_utilities.py
pyCoalesce/utilities/API_request.py
pyCoalesce/utilities/URL_class.py
pyCoalesce/utilities/__init__.py
pyCoalesce/utilities/logger.py
pyCoalesce-0.0.43.dev4.dist-info/LICENSE
pyCoalesce-0.0.43.dev4.dist-info/METADATA
pyCoalesce-0.0.43.dev4.dist-info/WHEEL
pyCoalesce-0.0.43.dev4.dist-info/top_level.txt
pyCoalesce-0.0.43.dev4.dist-info/RECORD
