Metadata-Version: 2.1
Name: pyCoalesce
Version: 0.0.43.dev4
Summary: A python wrapper for coalesce objects
Home-page: https://github.com/InCadence/coalesce/wiki
Author: Dhruva Venkat, Scott Orr
Author-email: sorr@incadencecorp.com
License: Apache License 2.0
Platform: UNKNOWN
Classifier: Programming Language :: Python :: 3.7
Classifier: License :: OSI Approved :: Apache Software License
Classifier: Operating System :: OS Independent
Requires-Dist: simplejson
Requires-Dist: xmltodict
Requires-Dist: requests
Requires-Dist: urllib3
